tests/lora/__init__.py
tests/lora/conftest.py
tests/lora/test_layers.py
tests/lora/test_llama.py
tests/lora/test_lora.py
tests/lora/test_lora_manager.py
tests/lora/test_punica.py
tests/lora/test_tokenizer.py
tests/lora/test_utils.py
tests/lora/test_worker.py
tests/lora/utils.py
tests/worker/__init__.py
tests/worker/test_model_runner.py
tests/worker/spec_decode/__init__.py
tests/worker/spec_decode/test_multi_step_worker.py
tests/worker/spec_decode/utils.py
tilearn/__init__.py
tilearn/infer/__init__.py
tilearn/infer/vllm/__init__.py
vllm/_C.cpython-310-x86_64-linux-gnu.so
vllm/_C.cpython-39-x86_64-linux-gnu.so
vllm/__init__.py
vllm/activation_ops.cpython-38-x86_64-linux-gnu.so
vllm/attention_ops.cpython-38-x86_64-linux-gnu.so
vllm/block.py
vllm/cache_ops.cpython-38-x86_64-linux-gnu.so
vllm/config.py
vllm/layernorm_ops.cpython-38-x86_64-linux-gnu.so
vllm/logger.py
vllm/outputs.py
vllm/pos_encoding_ops.cpython-38-x86_64-linux-gnu.so
vllm/prefix.py
vllm/py.typed
vllm/sampling_params.py
vllm/sequence.py
vllm/test_utils.py
vllm/utils.py
vllm/core/__init__.py
vllm/core/block_manager.py
vllm/core/policy.py
vllm/core/scheduler.py
vllm/engine/__init__.py
vllm/engine/arg_utils.py
vllm/engine/async_llm_engine.py
vllm/engine/llm_engine.py
vllm/engine/metrics.py
vllm/engine/ray_utils.py
vllm/entrypoints/__init__.py
vllm/entrypoints/api_server.py
vllm/entrypoints/llm.py
vllm/entrypoints/openai/__init__.py
vllm/entrypoints/openai/api_server.py
vllm/entrypoints/openai/protocol.py
vllm/entrypoints/openai/serving_chat.py
vllm/entrypoints/openai/serving_completion.py
vllm/entrypoints/openai/serving_engine.py
vllm/lora/__init__.py
vllm/lora/layers.py
vllm/lora/lora.py
vllm/lora/models.py
vllm/lora/punica.py
vllm/lora/request.py
vllm/lora/utils.py
vllm/lora/worker_manager.py
vllm/model_executor/__init__.py
vllm/model_executor/input_metadata.py
vllm/model_executor/model_loader.py
vllm/model_executor/sampling_metadata.py
vllm/model_executor/utils.py
vllm/model_executor/weight_utils.py
tilearn_test01-0.1.dist-info/LICENSE
tilearn_test01-0.1.dist-info/METADATA
tilearn_test01-0.1.dist-info/WHEEL
tilearn_test01-0.1.dist-info/top_level.txt
tilearn_test01-0.1.dist-info/RECORD
